agent_brain_server/__init__.py
agent_brain_server/api/__init__.py
agent_brain_server/api/main.py
agent_brain_server/api/routers/__init__.py
agent_brain_server/api/routers/health.py
agent_brain_server/api/routers/index.py
agent_brain_server/api/routers/query.py
agent_brain_server/config/__init__.py
agent_brain_server/config/settings.py
agent_brain_server/indexing/__init__.py
agent_brain_server/indexing/bm25_index.py
agent_brain_server/indexing/chunking.py
agent_brain_server/indexing/document_loader.py
agent_brain_server/indexing/embedding.py
agent_brain_server/locking.py
agent_brain_server/models/__init__.py
agent_brain_server/models/health.py
agent_brain_server/models/index.py
agent_brain_server/models/query.py
agent_brain_server/project_root.py
agent_brain_server/runtime.py
agent_brain_server/services/__init__.py
agent_brain_server/services/indexing_service.py
agent_brain_server/services/query_service.py
agent_brain_server/storage/__init__.py
agent_brain_server/storage/vector_store.py
agent_brain_server/storage_paths.py
agent_brain_rag-1.2.0.dist-info/METADATA
agent_brain_rag-1.2.0.dist-info/WHEEL
agent_brain_rag-1.2.0.dist-info/entry_points.txt
agent_brain_rag-1.2.0.dist-info/RECORD
