Metadata-Version: 2.3
Name: agent-brain-rag
Version: 1.2.0
Summary: Agent Brain RAG - Intelligent document indexing and semantic search server that gives AI agents long-term memory
License: MIT
Keywords: agent-brain,rag,semantic-search,ai-memory,llm-memory,documentation,indexing,llama-index,chromadb,ai-agent,claude-code,agent-memory
Author: Spillwave Solutions
Requires-Python: >=3.10,<4.0
Classifier: Development Status :: 4 - Beta
Classifier: Intended Audience :: Developers
Classifier: License :: OSI Approved :: MIT License
Classifier: Programming Language :: Python :: 3
Classifier: Programming Language :: Python :: 3.10
Classifier: Programming Language :: Python :: 3.11
Classifier: Programming Language :: Python :: 3.12
Classifier: Programming Language :: Python :: 3.13
Classifier: Topic :: Software Development :: Documentation
Classifier: Topic :: Text Processing :: Indexing
Requires-Dist: anthropic (>=0.40.0,<0.41.0)
Requires-Dist: chromadb (>=0.5.0,<0.6.0)
Requires-Dist: click (>=8.1.0,<9.0.0)
Requires-Dist: fastapi (>=0.115.0,<0.116.0)
Requires-Dist: llama-index-core (>=0.14.0,<0.15.0)
Requires-Dist: llama-index-embeddings-openai (>=0.5.0,<0.6.0)
Requires-Dist: llama-index-llms-openai (>=0.6.12,<0.7.0)
Requires-Dist: llama-index-readers-file (>=0.5.0,<0.6.0)
Requires-Dist: llama-index-retrievers-bm25 (>=0.6.0,<0.7.0)
Requires-Dist: openai (>=1.57.0,<2.0.0)
Requires-Dist: pydantic (>=2.10.0,<3.0.0)
Requires-Dist: pydantic-settings (>=2.6.0,<3.0.0)
Requires-Dist: python-dotenv (>=1.0.0,<2.0.0)
Requires-Dist: rank-bm25 (>=0.2.2,<0.3.0)
Requires-Dist: tiktoken (>=0.8.0,<0.9.0)
Requires-Dist: tree-sitter-language-pack (>=0.7.3,<0.8.0)
Requires-Dist: uvicorn[standard] (>=0.32.0,<0.33.0)
Project-URL: Documentation, https://github.com/SpillwaveSolutions/doc-serve#readme
Project-URL: Homepage, https://github.com/SpillwaveSolutions/doc-serve
Project-URL: Repository, https://github.com/SpillwaveSolutions/doc-serve
